CHANGES.txt
LICENSE.txt
MANIFEST.in
README.rst
conf.py
index.rst
setup.py
scripts/artifacts.py
scripts/make_docs.py
simplejson/__init__.py
simplejson/_speedups.c
simplejson/compat.py
simplejson/decoder.py
simplejson/encoder.py
simplejson/ordered_dict.py
simplejson/scanner.py
simplejson/tool.py
simplejson/tests/__init__.py
simplejson/tests/test_bigint_as_string.py
simplejson/tests/test_bitsize_int_as_string.py
simplejson/tests/test_check_circular.py
simplejson/tests/test_decimal.py
simplejson/tests/test_decode.py
simplejson/tests/test_default.py
simplejson/tests/test_dump.py
simplejson/tests/test_encode_basestring_ascii.py
simplejson/tests/test_encode_for_html.py
simplejson/tests/test_errors.py
simplejson/tests/test_fail.py
simplejson/tests/test_float.py
simplejson/tests/test_for_json.py
simplejson/tests/test_indent.py
simplejson/tests/test_item_sort_key.py
simplejson/tests/test_iterable.py
simplejson/tests/test_namedtuple.py
simplejson/tests/test_pass1.py
simplejson/tests/test_pass2.py
simplejson/tests/test_pass3.py
simplejson/tests/test_raw_json.py
simplejson/tests/test_recursion.py
simplejson/tests/test_scanstring.py
simplejson/tests/test_separators.py
simplejson/tests/test_speedups.py
simplejson/tests/test_str_subclass.py
simplejson/tests/test_subclass.py
simplejson/tests/test_tool.py
simplejson/tests/test_tuple.py
simplejson/tests/test_unicode.py
validjson.egg-info/PKG-INFO
validjson.egg-info/SOURCES.txt
validjson.egg-info/dependency_links.txt
validjson.egg-info/top_level.txt